verilog_week2/outlab/module.v
module getNextState (
    input [2:0] currentState,
    output [2:0] nextState
);

    wire a;
    wire b;
    wire c;
    assign c = currentState[0];
    assign b = currentState[1];
    assign a = currentState[2];
    assign nextState[2] = (a & ~b) | (a & ~c) | (~a & b & c);
    assign nextState[1] = (~b & c) | (b & ~c);
    assign nextState[0] = ~c;

endmodule

module threeBitCounter (
    input clk,
    input reset,
    output reg [2:0] count
    
);
    wire[2:0] count_new;
    getNextState gt(.currentState(count), .nextState(count_new));

    always @(posedge clk) begin
        if (reset==1'b1) begin
            count<=3'b000;
        end else begin
            count <= count_new;
        end
    end
endmodule

module counterToLights (
    input [2:0] count,
    output [2:0] rgb

);
    wire a;
    wire b;
    wire c;
   assign a=count[2];
   assign b=count[1];
   assign c=count[0];
   assign rgb[2] = ~b&~c | a&~b | ~a&b&c;//correct
   assign rgb[1] = ~b&~c | ~a&~b | ~a&~c;
   assign rgb[0] = b&~c | ~a&~c | a&~b&c;
endmodule

module rgbLighter (
    input clk,
    input reset,
    output [2:0] rgb
);
    wire[2:0] count;
    threeBitCounter cnt (.clk(clk), .reset(reset), .count(count));
    counterToLights ctl (.count(count), .rgb(rgb));

endmodule

verilog_week2/outlab/testbench.v
`timescale 1ns / 1ps

module tb_allModules;

    // ====== Testbench for rgbLighter (top module) ======
    reg clk;
    reg reset;
    wire [2:0] rgb;

    rgbLighter uut_rgbLighter (
        .clk(clk),
        .reset(reset),
        .rgb(rgb)
    );

    integer i;

    // Clock generation for rgbLighter and threeBitCounter
    initial clk = 0;
    always #5 clk = ~clk;  // 10ns period

    initial begin
        $display("=== rgbLighter test ===");
        $display("Time\tclk\treset\trgb");
        $monitor("%0dns\t%b\t%b\t%03b", $time, clk, reset, rgb);

        $dumpfile("wave.vcd");
        $dumpvars(0, tb_allModules);

        reset = 1;
        #10;
        reset = 0;

        #200;
        $display("=== End rgbLighter test ===\n");
        $monitoroff; 
    end


    // ====== Testbench for getNextState ======
    reg [2:0] currentState;
    wire [2:0] nextState;

    getNextState uut_getNextState (
        .currentState(currentState),
        .nextState(nextState)
    );

    initial begin
        #220;  // Wait for rgbLighter test to finish
        $display("=== getNextState test ===");
        $display("CurrentState | NextState");
        for (i = 0; i < 8; i = i + 1) begin
            currentState = i;
            #10;
            $display("    %b     |    %b", currentState, nextState);
        end
        $display("=== End getNextState test ===\n");
    end


    // ====== Testbench for threeBitCounter ======
    reg tb_clk;
    reg tb_reset;
    wire [2:0] tb_count;

    threeBitCounter uut_threeBitCounter (
        .clk(tb_clk),
        .reset(tb_reset),
        .count(tb_count)
    );

    // Separate clock for threeBitCounter
    initial tb_clk = 0;
    always #7 tb_clk = ~tb_clk;  // 14ns period to distinguish from rgbLighter clk

    initial begin
        #500;  // Wait for previous tests
        $display("=== threeBitCounter test ===");
        tb_reset = 1;
        #14;
        tb_reset = 0;

        // Run for 10 clock cycles of tb_clk
        repeat (10) @(posedge tb_clk) 
            $display("At time %0t ns, count = %b", $time, tb_count);

        $display("=== End threeBitCounter test ===\n");
    end


    // ====== Testbench for counterToLights ======
    reg [2:0] inputCount;
    wire [2:0] rgb_out;

    counterToLights uut_counterToLights (
        .count(inputCount),
        .rgb(rgb_out)
    );

    initial begin
        #1000;  // Wait for previous tests
        $display("=== counterToLights test ===");
        $display("Count | RGB");
        for (i = 0; i < 8; i = i + 1) begin
            inputCount = i;
            #10;
            $display(" %03b  | %03b", inputCount, rgb_out);
        end
        $display("=== End counterToLights test ===\n");
        $finish;
    end

endmodule

verilog_week2/outlab/wave.vcd
$date
	Wed Aug 13 22:08:11 2025
$end
$version
	Icarus Verilog
$end
$timescale
	1ps
$end
$scope module tb_allModules $end
$var wire 3 ! tb_count [2:0] $end
$var wire 3 " rgb_out [2:0] $end
$var wire 3 # rgb [2:0] $end
$var wire 3 $ nextState [2:0] $end
$var reg 1 % clk $end
$var reg 3 & currentState [2:0] $end
$var reg 3 ' inputCount [2:0] $end
$var reg 1 ( reset $end
$var reg 1 ) tb_clk $end
$var reg 1 * tb_reset $end
$var integer 32 + i [31:0] $end
$scope module uut_counterToLights $end
$var wire 3 , count [2:0] $end
$var wire 3 - rgb [2:0] $end
$var wire 1 . c $end
$var wire 1 / b $end
$var wire 1 0 a $end
$upscope $end
$scope module uut_getNextState $end
$var wire 3 1 currentState [2:0] $end
$var wire 3 2 nextState [2:0] $end
$var wire 1 3 c $end
$var wire 1 4 b $end
$var wire 1 5 a $end
$upscope $end
$scope module uut_rgbLighter $end
$var wire 1 % clk $end
$var wire 1 ( reset $end
$var wire 3 6 rgb [2:0] $end
$var wire 3 7 count [2:0] $end
$scope module cnt $end
$var wire 1 % clk $end
$var wire 1 ( reset $end
$var wire 3 8 count_new [2:0] $end
$var reg 3 9 count [2:0] $end
$scope module gt $end
$var wire 3 : currentState [2:0] $end
$var wire 3 ; nextState [2:0] $end
$var wire 1 < c $end
$var wire 1 = b $end
$var wire 1 > a $end
$upscope $end
$upscope $end
$scope module ctl $end
$var wire 3 ? count [2:0] $end
$var wire 3 @ rgb [2:0] $end
$var wire 1 A c $end
$var wire 1 B b $end
$var wire 1 C a $end
$upscope $end
$upscope $end
$scope module uut_threeBitCounter $end
$var wire 1 ) clk $end
$var wire 1 * reset $end
$var wire 3 D count_new [2:0] $end
$var reg 3 E count [2:0] $end
$scope module gt $end
$var wire 3 F currentState [2:0] $end
$var wire 3 G nextState [2:0] $end
$var wire 1 H c $end
$var wire 1 I b $end
$var wire 1 J a $end
$upscope $end
$upscope $end
$upscope $end
$enddefinitions $end
$comment Show the parameter values. $end
$dumpall
$end
#0
$dumpvars
xJ
xI
xH
bx G
bx F
bx E
bx D
xC
xB
xA
bx @
bx ?
x>
x=
x<
bx ;
bx :
bx 9
bx 8
bx 7
bx 6
x5
x4
x3
bx 2
bx 1
x0
x/
x.
bx -
bx ,
bx +
x*
0)
1(
bx '
bx &
0%
bx $
bx #
bx "
bx !
$end
#5000
b111 #
b111 6
b111 @
b1 8
b1 ;
0<
0=
0>
0C
0B
0A
b0 7
b0 9
b0 :
b0 ?
1%
#7000
1)
#10000
0%
0(
#14000
0)
#15000
b10 #
b10 6
b10 @
b10 8
b10 ;
1<
1A
b1 7
b1 9
b1 :
b1 ?
1%
#20000
0%
#21000
1)
#25000
b11 #
b11 6
b11 @
b11 8
b11 ;
0<
1=
1B
0A
b10 7
b10 9
b10 :
b10 ?
1%
#28000
0)
#30000
0%
#35000
b100 #
b100 6
b100 @
b100 8
b100 ;
1<
1A
b11 7
b11 9
b11 :
b11 ?
1%
1)
#40000
0%
#42000
0)
#45000
b110 #
b110 6
b110 @
b101 8
b101 ;
0<
0=
1>
1C
0B
0A
b100 7
b100 9
b100 :
b100 ?
1%
#49000
1)
#50000
0%
#55000
b101 #
b101 6
b101 @
b110 8
b110 ;
1<
1A
b101 7
b101 9
b101 :
b101 ?
1%
#56000
0)
#60000
0%
#63000
1)
#65000
b1 #
b1 6
b1 @
b111 8
b111 ;
0<
1=
1B
0A
b110 7
b110 9
b110 :
b110 ?
1%
#70000
0%
0)
#75000
b0 #
b0 6
b0 @
b0 8
b0 ;
1<
1A
b111 7
b111 9
b111 :
b111 ?
1%
#77000
1)
#80000
0%
#84000
0)
#85000
b111 #
b111 6
b111 @
b1 8
b1 ;
0<
0=
0>
0C
0B
0A
b0 7
b0 9
b0 :
b0 ?
1%
#90000
0%
#91000
1)
#95000
b10 #
b10 6
b10 @
b10 8
b10 ;
1<
1A
b1 7
b1 9
b1 :
b1 ?
1%
#98000
0)
#100000
0%
#105000
b11 #
b11 6
b11 @
b11 8
b11 ;
0<
1=
1B
0A
b10 7
b10 9
b10 :
b10 ?
1%
1)
#110000
0%
#112000
0)
#115000
b100 #
b100 6
b100 @
b100 8
b100 ;
1<
1A
b11 7
b11 9
b11 :
b11 ?
1%
#119000
1)
#120000
0%
#125000
b110 #
b110 6
b110 @
b101 8
b101 ;
0<
0=
1>
1C
0B
0A
b100 7
b100 9
b100 :
b100 ?
1%
#126000
0)
#130000
0%
#133000
1)
#135000
b101 #
b101 6
b101 @
b110 8
b110 ;
1<
1A
b101 7
b101 9
b101 :
b101 ?
1%
#140000
0%
0)
#145000
b1 #
b1 6
b1 @
b111 8
b111 ;
0<
1=
1B
0A
b110 7
b110 9
b110 :
b110 ?
1%
#147000
1)
#150000
0%
#154000
0)
#155000
b0 #
b0 6
b0 @
b0 8
b0 ;
1<
1A
b111 7
b111 9
b111 :
b111 ?
1%
#160000
0%
#161000
1)
#165000
b111 #
b111 6
b111 @
b1 8
b1 ;
0<
0=
0>
0C
0B
0A
b0 7
b0 9
b0 :
b0 ?
1%
#168000
0)
#170000
0%
#175000
b10 #
b10 6
b10 @
b10 8
b10 ;
1<
1A
b1 7
b1 9
b1 :
b1 ?
1%
1)
#180000
0%
#182000
0)
#185000
b11 #
b11 6
b11 @
b11 8
b11 ;
0<
1=
1B
0A
b10 7
b10 9
b10 :
b10 ?
1%
#189000
1)
#190000
0%
#195000
b100 #
b100 6
b100 @
b100 8
b100 ;
1<
1A
b11 7
b11 9
b11 :
b11 ?
1%
#196000
0)
#200000
0%
#203000
1)
#205000
b110 #
b110 6
b110 @
b101 8
b101 ;
0<
0=
1>
1C
0B
0A
b100 7
b100 9
b100 :
b100 ?
1%
#210000
0%
0)
#215000
b101 #
b101 6
b101 @
b110 8
b110 ;
1<
1A
b101 7
b101 9
b101 :
b101 ?
1%
#217000
1)
#220000
b1 $
b1 2
03
04
05
0%
b0 &
b0 1
b0 +
#224000
0)
#225000
b1 #
b1 6
b1 @
b111 8
b111 ;
0<
1=
1B
0A
b110 7
b110 9
b110 :
b110 ?
1%
#230000
b10 $
b10 2
13
0%
b1 &
b1 1
b1 +
#231000
1)
#235000
b0 #
b0 6
b0 @
b0 8
b0 ;
1<
1A
b111 7
b111 9
b111 :
b111 ?
1%
#238000
0)
#240000
b11 $
b11 2
03
14
0%
b10 &
b10 1
b10 +
#245000
b111 #
b111 6
b111 @
b1 8
b1 ;
0<
0=
0>
0C
0B
0A
b0 7
b0 9
b0 :
b0 ?
1%
1)
#250000
b100 $
b100 2
13
0%
b11 &
b11 1
b11 +
#252000
0)
#255000
b10 #
b10 6
b10 @
b10 8
b10 ;
1<
1A
b1 7
b1 9
b1 :
b1 ?
1%
#259000
1)
#260000
b101 $
b101 2
03
04
15
0%
b100 &
b100 1
b100 +
#265000
b11 #
b11 6
b11 @
b11 8
b11 ;
0<
1=
1B
0A
b10 7
b10 9
b10 :
b10 ?
1%
#266000
0)
#270000
b110 $
b110 2
13
0%
b101 &
b101 1
b101 +
#273000
1)
#275000
b100 #
b100 6
b100 @
b100 8
b100 ;
1<
1A
b11 7
b11 9
b11 :
b11 ?
1%
#280000
b111 $
b111 2
03
14
0%
0)
b110 &
b110 1
b110 +
#285000
b110 #
b110 6
b110 @
b101 8
b101 ;
0<
0=
1>
1C
0B
0A
b100 7
b100 9
b100 :
b100 ?
1%
#287000
1)
#290000
b0 $
b0 2
13
0%
b111 &
b111 1
b111 +
#294000
0)
#295000
b101 #
b101 6
b101 @
b110 8
b110 ;
1<
1A
b101 7
b101 9
b101 :
b101 ?
1%
#300000
0%
b1000 +
#301000
1)
#305000
b1 #
b1 6
b1 @
b111 8
b111 ;
0<
1=
1B
0A
b110 7
b110 9
b110 :
b110 ?
1%
#308000
0)
#310000
0%
#315000
b0 #
b0 6
b0 @
b0 8
b0 ;
1<
1A
b111 7
b111 9
b111 :
b111 ?
1%
1)
#320000
0%
#322000
0)
#325000
b111 #
b111 6
b111 @
b1 8
b1 ;
0<
0=
0>
0C
0B
0A
b0 7
b0 9
b0 :
b0 ?
1%
#329000
1)
#330000
0%
#335000
b10 #
b10 6
b10 @
b10 8
b10 ;
1<
1A
b1 7
b1 9
b1 :
b1 ?
1%
#336000
0)
#340000
0%
#343000
1)
#345000
b11 #
b11 6
b11 @
b11 8
b11 ;
0<
1=
1B
0A
b10 7
b10 9
b10 :
b10 ?
1%
#350000
0%
0)
#355000
b100 #
b100 6
b100 @
b100 8
b100 ;
1<
1A
b11 7
b11 9
b11 :
b11 ?
1%
#357000
1)
#360000
0%
#364000
0)
#365000
b110 #
b110 6
b110 @
b101 8
b101 ;
0<
0=
1>
1C
0B
0A
b100 7
b100 9
b100 :
b100 ?
1%
#370000
0%
#371000
1)
#375000
b101 #
b101 6
b101 @
b110 8
b110 ;
1<
1A
b101 7
b101 9
b101 :
b101 ?
1%
#378000
0)
#380000
0%
#385000
b1 #
b1 6
b1 @
b111 8
b111 ;
0<
1=
1B
0A
b110 7
b110 9
b110 :
b110 ?
1%
1)
#390000
0%
#392000
0)
#395000
b0 #
b0 6
b0 @
b0 8
b0 ;
1<
1A
b111 7
b111 9
b111 :
b111 ?
1%
#399000
1)
#400000
0%
#405000
b111 #
b111 6
b111 @
b1 8
b1 ;
0<
0=
0>
0C
0B
0A
b0 7
b0 9
b0 :
b0 ?
1%
#406000
0)
#410000
0%
#413000
1)
#415000
b10 #
b10 6
b10 @
b10 8
b10 ;
1<
1A
b1 7
b1 9
b1 :
b1 ?
1%
#420000
0%
0)
#425000
b11 #
b11 6
b11 @
b11 8
b11 ;
0<
1=
1B
0A
b10 7
b10 9
b10 :
b10 ?
1%
#427000
1)
#430000
0%
#434000
0)
#435000
b100 #
b100 6
b100 @
b100 8
b100 ;
1<
1A
b11 7
b11 9
b11 :
b11 ?
1%
#440000
0%
#441000
1)
#445000
b110 #
b110 6
b110 @
b101 8
b101 ;
0<
0=
1>
1C
0B
0A
b100 7
b100 9
b100 :
b100 ?
1%
#448000
0)
#450000
0%
#455000
b101 #
b101 6
b101 @
b110 8
b110 ;
1<
1A
b101 7
b101 9
b101 :
b101 ?
1%
1)
#460000
0%
#462000
0)
#465000
b1 #
b1 6
b1 @
b111 8
b111 ;
0<
1=
1B
0A
b110 7
b110 9
b110 :
b110 ?
1%
#469000
1)
#470000
0%
#475000
b0 #
b0 6
b0 @
b0 8
b0 ;
1<
1A
b111 7
b111 9
b111 :
b111 ?
1%
#476000
0)
#480000
0%
#483000
1)
#485000
b111 #
b111 6
b111 @
b1 8
b1 ;
0<
0=
0>
0C
0B
0A
b0 7
b0 9
b0 :
b0 ?
1%
#490000
0%
0)
#495000
b10 #
b10 6
b10 @
b10 8
b10 ;
1<
1A
b1 7
b1 9
b1 :
b1 ?
1%
#497000
1)
#500000
0%
1*
#504000
0)
#505000
b11 #
b11 6
b11 @
b11 8
b11 ;
0<
1=
1B
0A
b10 7
b10 9
b10 :
b10 ?
1%
#510000
0%
#511000
b1 D
b1 G
0H
0I
0J
b0 !
b0 E
b0 F
1)
#514000
0*
#515000
b100 #
b100 6
b100 @
b100 8
b100 ;
1<
1A
b11 7
b11 9
b11 :
b11 ?
1%
#518000
0)
#520000
0%
#525000
b110 #
b110 6
b110 @
b101 8
b101 ;
b10 D
b10 G
0<
0=
1>
1C
0B
0A
1H
b100 7
b100 9
b100 :
b100 ?
b1 !
b1 E
b1 F
1%
1)
#530000
0%
#532000
0)
#535000
b101 #
b101 6
b101 @
b110 8
b110 ;
1<
1A
b101 7
b101 9
b101 :
b101 ?
1%
#539000
b11 D
b11 G
0H
1I
b10 !
b10 E
b10 F
1)
#540000
0%
#545000
b1 #
b1 6
b1 @
b111 8
b111 ;
0<
1=
1B
0A
b110 7
b110 9
b110 :
b110 ?
1%
#546000
0)
#550000
0%
#553000
b100 D
b100 G
1H
b11 !
b11 E
b11 F
1)
#555000
b0 #
b0 6
b0 @
b0 8
b0 ;
1<
1A
b111 7
b111 9
b111 :
b111 ?
1%
#560000
0%
0)
#565000
b111 #
b111 6
b111 @
b1 8
b1 ;
0<
0=
0>
0C
0B
0A
b0 7
b0 9
b0 :
b0 ?
1%
#567000
b101 D
b101 G
0H
0I
1J
b100 !
b100 E
b100 F
1)
#570000
0%
#574000
0)
#575000
b10 #
b10 6
b10 @
b10 8
b10 ;
1<
1A
b1 7
b1 9
b1 :
b1 ?
1%
#580000
0%
#581000
b110 D
b110 G
1H
b101 !
b101 E
b101 F
1)
#585000
b11 #
b11 6
b11 @
b11 8
b11 ;
0<
1=
1B
0A
b10 7
b10 9
b10 :
b10 ?
1%
#588000
0)
#590000
0%
#595000
b100 #
b100 6
b100 @
b100 8
b100 ;
b111 D
b111 G
1<
1A
0H
1I
b11 7
b11 9
b11 :
b11 ?
b110 !
b110 E
b110 F
1%
1)
#600000
0%
#602000
0)
#605000
b110 #
b110 6
b110 @
b101 8
b101 ;
0<
0=
1>
1C
0B
0A
b100 7
b100 9
b100 :
b100 ?
1%
#609000
b0 D
b0 G
1H
b111 !
b111 E
b111 F
1)
#610000
0%
#615000
b101 #
b101 6
b101 @
b110 8
b110 ;
1<
1A
b101 7
b101 9
b101 :
b101 ?
1%
#616000
0)
#620000
0%
#623000
b1 D
b1 G
0H
0I
0J
b0 !
b0 E
b0 F
1)
#625000
b1 #
b1 6
b1 @
b111 8
b111 ;
0<
1=
1B
0A
b110 7
b110 9
b110 :
b110 ?
1%
#630000
0%
0)
#635000
b0 #
b0 6
b0 @
b0 8
b0 ;
1<
1A
b111 7
b111 9
b111 :
b111 ?
1%
#637000
b10 D
b10 G
1H
b1 !
b1 E
b1 F
1)
#640000
0%
#644000
0)
#645000
b111 #
b111 6
b111 @
b1 8
b1 ;
0<
0=
0>
0C
0B
0A
b0 7
b0 9
b0 :
b0 ?
1%
#650000
0%
#651000
b11 D
b11 G
0H
1I
b10 !
b10 E
b10 F
1)
#655000
b10 #
b10 6
b10 @
b10 8
b10 ;
1<
1A
b1 7
b1 9
b1 :
b1 ?
1%
#658000
0)
#660000
0%
#665000
b11 #
b11 6
b11 @
b11 8
b11 ;
b100 D
b100 G
0<
1=
1B
0A
1H
b10 7
b10 9
b10 :
b10 ?
b11 !
b11 E
b11 F
1%
1)
#670000
0%
#672000
0)
#675000
b100 #
b100 6
b100 @
b100 8
b100 ;
1<
1A
b11 7
b11 9
b11 :
b11 ?
1%
#679000
b101 D
b101 G
0H
0I
1J
b100 !
b100 E
b100 F
1)
#680000
0%
#685000
b110 #
b110 6
b110 @
b101 8
b101 ;
0<
0=
1>
1C
0B
0A
b100 7
b100 9
b100 :
b100 ?
1%
#686000
0)
#690000
0%
#693000
b110 D
b110 G
1H
b101 !
b101 E
b101 F
1)
#695000
b101 #
b101 6
b101 @
b110 8
b110 ;
1<
1A
b101 7
b101 9
b101 :
b101 ?
1%
#700000
0%
0)
#705000
b1 #
b1 6
b1 @
b111 8
b111 ;
0<
1=
1B
0A
b110 7
b110 9
b110 :
b110 ?
1%
#707000
b111 D
b111 G
0H
1I
b110 !
b110 E
b110 F
1)
#710000
0%
#714000
0)
#715000
b0 #
b0 6
b0 @
b0 8
b0 ;
1<
1A
b111 7
b111 9
b111 :
b111 ?
1%
#720000
0%
#721000
b0 D
b0 G
1H
b111 !
b111 E
b111 F
1)
#725000
b111 #
b111 6
b111 @
b1 8
b1 ;
0<
0=
0>
0C
0B
0A
b0 7
b0 9
b0 :
b0 ?
1%
#728000
0)
#730000
0%
#735000
b10 #
b10 6
b10 @
b10 8
b10 ;
b1 D
b1 G
1<
1A
0H
0I
0J
b1 7
b1 9
b1 :
b1 ?
b0 !
b0 E
b0 F
1%
1)
#740000
0%
#742000
0)
#745000
b11 #
b11 6
b11 @
b11 8
b11 ;
0<
1=
1B
0A
b10 7
b10 9
b10 :
b10 ?
1%
#749000
b10 D
b10 G
1H
b1 !
b1 E
b1 F
1)
#750000
0%
#755000
b100 #
b100 6
b100 @
b100 8
b100 ;
1<
1A
b11 7
b11 9
b11 :
b11 ?
1%
#756000
0)
#760000
0%
#763000
b11 D
b11 G
0H
1I
b10 !
b10 E
b10 F
1)
#765000
b110 #
b110 6
b110 @
b101 8
b101 ;
0<
0=
1>
1C
0B
0A
b100 7
b100 9
b100 :
b100 ?
1%
#770000
0%
0)
#775000
b101 #
b101 6
b101 @
b110 8
b110 ;
1<
1A
b101 7
b101 9
b101 :
b101 ?
1%
#777000
b100 D
b100 G
1H
b11 !
b11 E
b11 F
1)
#780000
0%
#784000
0)
#785000
b1 #
b1 6
b1 @
b111 8
b111 ;
0<
1=
1B
0A
b110 7
b110 9
b110 :
b110 ?
1%
#790000
0%
#791000
b101 D
b101 G
0H
0I
1J
b100 !
b100 E
b100 F
1)
#795000
b0 #
b0 6
b0 @
b0 8
b0 ;
1<
1A
b111 7
b111 9
b111 :
b111 ?
1%
#798000
0)
#800000
0%
#805000
b111 #
b111 6
b111 @
b1 8
b1 ;
b110 D
b110 G
0<
0=
0>
0C
0B
0A
1H
b0 7
b0 9
b0 :
b0 ?
b101 !
b101 E
b101 F
1%
1)
#810000
0%
#812000
0)
#815000
b10 #
b10 6
b10 @
b10 8
b10 ;
1<
1A
b1 7
b1 9
b1 :
b1 ?
1%
#819000
b111 D
b111 G
0H
1I
b110 !
b110 E
b110 F
1)
#820000
0%
#825000
b11 #
b11 6
b11 @
b11 8
b11 ;
0<
1=
1B
0A
b10 7
b10 9
b10 :
b10 ?
1%
#826000
0)
#830000
0%
#833000
b0 D
b0 G
1H
b111 !
b111 E
b111 F
1)
#835000
b100 #
b100 6
b100 @
b100 8
b100 ;
1<
1A
b11 7
b11 9
b11 :
b11 ?
1%
#840000
0%
0)
#845000
b110 #
b110 6
b110 @
b101 8
b101 ;
0<
0=
1>
1C
0B
0A
b100 7
b100 9
b100 :
b100 ?
1%
#847000
b1 D
b1 G
0H
0I
0J
b0 !
b0 E
b0 F
1)
#850000
0%
#854000
0)
#855000
b101 #
b101 6
b101 @
b110 8
b110 ;
1<
1A
b101 7
b101 9
b101 :
b101 ?
1%
#860000
0%
#861000
b10 D
b10 G
1H
b1 !
b1 E
b1 F
1)
#865000
b1 #
b1 6
b1 @
b111 8
b111 ;
0<
1=
1B
0A
b110 7
b110 9
b110 :
b110 ?
1%
#868000
0)
#870000
0%
#875000
b0 #
b0 6
b0 @
b0 8
b0 ;
b11 D
b11 G
1<
1A
0H
1I
b111 7
b111 9
b111 :
b111 ?
b10 !
b10 E
b10 F
1%
1)
#880000
0%
#882000
0)
#885000
b111 #
b111 6
b111 @
b1 8
b1 ;
0<
0=
0>
0C
0B
0A
b0 7
b0 9
b0 :
b0 ?
1%
#889000
b100 D
b100 G
1H
b11 !
b11 E
b11 F
1)
#890000
0%
#895000
b10 #
b10 6
b10 @
b10 8
b10 ;
1<
1A
b1 7
b1 9
b1 :
b1 ?
1%
#896000
0)
#900000
0%
#903000
b101 D
b101 G
0H
0I
1J
b100 !
b100 E
b100 F
1)
#905000
b11 #
b11 6
b11 @
b11 8
b11 ;
0<
1=
1B
0A
b10 7
b10 9
b10 :
b10 ?
1%
#910000
0%
0)
#915000
b100 #
b100 6
b100 @
b100 8
b100 ;
1<
1A
b11 7
b11 9
b11 :
b11 ?
1%
#917000
b110 D
b110 G
1H
b101 !
b101 E
b101 F
1)
#920000
0%
#924000
0)
#925000
b110 #
b110 6
b110 @
b101 8
b101 ;
0<
0=
1>
1C
0B
0A
b100 7
b100 9
b100 :
b100 ?
1%
#930000
0%
#931000
b111 D
b111 G
0H
1I
b110 !
b110 E
b110 F
1)
#935000
b101 #
b101 6
b101 @
b110 8
b110 ;
1<
1A
b101 7
b101 9
b101 :
b101 ?
1%
#938000
0)
#940000
0%
#945000
b1 #
b1 6
b1 @
b111 8
b111 ;
b0 D
b0 G
0<
1=
1B
0A
1H
b110 7
b110 9
b110 :
b110 ?
b111 !
b111 E
b111 F
1%
1)
#950000
0%
#952000
0)
#955000
b0 #
b0 6
b0 @
b0 8
b0 ;
1<
1A
b111 7
b111 9
b111 :
b111 ?
1%
#959000
b1 D
b1 G
0H
0I
0J
b0 !
b0 E
b0 F
1)
#960000
0%
#965000
b111 #
b111 6
b111 @
b1 8
b1 ;
0<
0=
0>
0C
0B
0A
b0 7
b0 9
b0 :
b0 ?
1%
#966000
0)
#970000
0%
#973000
b10 D
b10 G
1H
b1 !
b1 E
b1 F
1)
#975000
b10 #
b10 6
b10 @
b10 8
b10 ;
1<
1A
b1 7
b1 9
b1 :
b1 ?
1%
#980000
0%
0)
#985000
b11 #
b11 6
b11 @
b11 8
b11 ;
0<
1=
1B
0A
b10 7
b10 9
b10 :
b10 ?
1%
#987000
b11 D
b11 G
0H
1I
b10 !
b10 E
b10 F
1)
#990000
0%
#994000
0)
#995000
b100 #
b100 6
b100 @
b100 8
b100 ;
1<
1A
b11 7
b11 9
b11 :
b11 ?
1%
#1000000
b111 "
b111 -
00
0/
0.
0%
b0 '
b0 ,
b0 +
#1001000
b100 D
b100 G
1H
b11 !
b11 E
b11 F
1)
#1005000
b110 #
b110 6
b110 @
b101 8
b101 ;
0<
0=
1>
1C
0B
0A
b100 7
b100 9
b100 :
b100 ?
1%
#1008000
0)
#1010000
b10 "
b10 -
1.
0%
b1 '
b1 ,
b1 +
#1015000
b101 #
b101 6
b101 @
b110 8
b110 ;
b101 D
b101 G
1<
1A
0H
0I
1J
b101 7
b101 9
b101 :
b101 ?
b100 !
b100 E
b100 F
1%
1)
#1020000
b11 "
b11 -
1/
0.
0%
b10 '
b10 ,
b10 +
#1022000
0)
#1025000
b1 #
b1 6
b1 @
b111 8
b111 ;
0<
1=
1B
0A
b110 7
b110 9
b110 :
b110 ?
1%
#1029000
b110 D
b110 G
1H
b101 !
b101 E
b101 F
1)
#1030000
b100 "
b100 -
1.
0%
b11 '
b11 ,
b11 +
#1035000
b0 #
b0 6
b0 @
b0 8
b0 ;
1<
1A
b111 7
b111 9
b111 :
b111 ?
1%
#1036000
0)
#1040000
b110 "
b110 -
10
0/
0.
0%
b100 '
b100 ,
b100 +
#1043000
b111 D
b111 G
0H
1I
b110 !
b110 E
b110 F
1)
#1045000
b111 #
b111 6
b111 @
b1 8
b1 ;
0<
0=
0>
0C
0B
0A
b0 7
b0 9
b0 :
b0 ?
1%
#1050000
b101 "
b101 -
1.
0%
0)
b101 '
b101 ,
b101 +
#1055000
b10 #
b10 6
b10 @
b10 8
b10 ;
1<
1A
b1 7
b1 9
b1 :
b1 ?
1%
#1057000
b0 D
b0 G
1H
b111 !
b111 E
b111 F
1)
#1060000
b1 "
b1 -
1/
0.
0%
b110 '
b110 ,
b110 +
#1064000
0)
#1065000
b11 #
b11 6
b11 @
b11 8
b11 ;
0<
1=
1B
0A
b10 7
b10 9
b10 :
b10 ?
1%
#1070000
b0 "
b0 -
1.
0%
b111 '
b111 ,
b111 +
#1071000
b1 D
b1 G
0H
0I
0J
b0 !
b0 E
b0 F
1)
#1075000
b100 #
b100 6
b100 @
b100 8
b100 ;
1<
1A
b11 7
b11 9
b11 :
b11 ?
1%
#1078000
0)
#1080000
0%
b1000 +
